[
  {
    "id": "starter-en-common-stories",
    "title": "1000 Most Common English Words: Stories",
    "author": "Word Hunter Originals",
    "lang": "en",
    "level": "Beginner",
    "blurb": "Original short stories about home, school, work, travel, health, nature, and everyday community life.",
    "localPath": "books/starter/en-stories.txt",
    "coverPath": "books/starter/en-cover.svg",
    "source": "Word Hunter Originals"
  },
  {
    "id": "starter-de-common-stories",
    "title": "1000 häufigste deutsche Wörter: Geschichten",
    "author": "Word Hunter Originals",
    "lang": "de",
    "level": "Beginner",
    "blurb": "Original short stories built around common German vocabulary and familiar everyday situations.",
    "localPath": "books/starter/de-stories.txt",
    "coverPath": "books/starter/de-cover.svg",
    "source": "Word Hunter Originals"
  },
  {
    "id": "starter-es-common-stories",
    "title": "Las 1000 palabras más frecuentes en español: Historias",
    "author": "Word Hunter Originals",
    "lang": "es",
    "level": "Beginner",
    "blurb": "Original short stories built around common Spanish vocabulary and familiar everyday situations.",
    "localPath": "books/starter/es-stories.txt",
    "coverPath": "books/starter/es-cover.svg",
    "source": "Word Hunter Originals"
  },
  {
    "id": "starter-fr-common-stories",
    "title": "Les 1000 mots français les plus fréquents : Histoires",
    "author": "Word Hunter Originals",
    "lang": "fr",
    "level": "Beginner",
    "blurb": "Original short stories built around common French vocabulary and familiar everyday situations.",
    "localPath": "books/starter/fr-stories.txt",
    "coverPath": "books/starter/fr-cover.svg",
    "source": "Word Hunter Originals"
  },
  {
    "id": "starter-it-common-stories",
    "title": "Le 1000 parole italiane più frequenti: Storie",
    "author": "Word Hunter Originals",
    "lang": "it",
    "level": "Beginner",
    "blurb": "Original short stories built around common Italian vocabulary and familiar everyday situations.",
    "localPath": "books/starter/it-stories.txt",
    "coverPath": "books/starter/it-cover.svg",
    "source": "Word Hunter Originals"
  },
  {
    "id": "starter-pl-common-stories",
    "title": "1000 najczęstszych polskich słów: Historyjki",
    "author": "Word Hunter Originals",
    "lang": "pl",
    "level": "Beginner",
    "blurb": "Original short stories built around common Polish vocabulary and familiar everyday situations.",
    "localPath": "books/starter/pl-stories.txt",
    "coverPath": "books/starter/pl-cover.svg",
    "source": "Word Hunter Originals"
  },
  {
    "id": "starter-uk-common-stories",
    "title": "1000 найуживаніших українських слів: Історії",
    "author": "Word Hunter Originals",
    "lang": "uk",
    "level": "Beginner",
    "blurb": "Original short stories built around common Ukrainian vocabulary and familiar everyday situations.",
    "localPath": "books/starter/uk-stories.txt",
    "coverPath": "books/starter/uk-cover.svg",
    "source": "Word Hunter Originals"
  },
  {
    "id": "starter-ru-common-stories",
    "title": "1000 самых частых русских слов: Истории",
    "author": "Word Hunter Originals",
    "lang": "ru",
    "level": "Beginner",
    "blurb": "Original short stories built around common Russian vocabulary and familiar everyday situations.",
    "localPath": "books/starter/ru-stories.txt",
    "coverPath": "books/starter/ru-cover.svg",
    "source": "Word Hunter Originals"
  },
  {
    "id": "starter-ja-common-stories",
    "title": "よく使う日本語1000語の物語",
    "author": "Word Hunter Originals",
    "lang": "ja",
    "level": "Beginner",
    "blurb": "Original short stories built around common Japanese vocabulary and familiar everyday situations.",
    "localPath": "books/starter/ja-stories.txt",
    "coverPath": "books/starter/ja-cover.svg",
    "source": "Word Hunter Originals"
  },
  {
    "id": "starter-zh-common-stories",
    "title": "最常用的1000个中文词：小故事",
    "author": "Word Hunter Originals",
    "lang": "zh",
    "level": "Beginner",
    "blurb": "Original short stories built around common Chinese vocabulary and familiar everyday situations.",
    "localPath": "books/starter/zh-stories.txt",
    "coverPath": "books/starter/zh-cover.svg",
    "source": "Word Hunter Originals"
  },
  {
    "id": "starter-la-common-stories",
    "title": "Mille Verba Latina Frequentissima: Fabulae",
    "author": "Word Hunter Originals",
    "lang": "la",
    "level": "Beginner",
    "blurb": "Original short stories built around frequent Latin vocabulary and scenes from daily life.",
    "localPath": "books/starter/la-stories.txt",
    "coverPath": "books/starter/la-cover.svg",
    "source": "Word Hunter Originals"
  },
  {
    "id": "starter-grc-common-stories",
    "title": "Χίλιαι Λέξεις: Μικραὶ Ἱστορίαι",
    "author": "Word Hunter Originals",
    "lang": "grc",
    "level": "Beginner",
    "blurb": "Original short stories built around frequent Ancient Greek vocabulary and scenes from daily life.",
    "localPath": "books/starter/grc-stories.txt",
    "coverPath": "books/starter/grc-cover.svg",
    "source": "Word Hunter Originals"
  },
  {
    "id": "starter-en-a1-course",
    "title": "Lantern House: An A1 Graded Reader",
    "author": "Word Hunter Originals",
    "lang": "en",
    "level": "A1",
    "blurb": "An original A1 graded reader for reading comprehension and contextual vocabulary only.",
    "localPath": "books/starter/en-a1-course.txt",
    "coverPath": "books/starter/en-a1-course-cover.svg",
    "source": "Word Hunter Originals"
  },
  {
    "id": "starter-en-a2-course",
    "title": "A Stage by the Sea: An A2 Graded Reader",
    "author": "Word Hunter Originals",
    "lang": "en",
    "level": "A2",
    "blurb": "An original A2 graded reader for reading comprehension and contextual vocabulary only.",
    "localPath": "books/starter/en-a2-course.txt",
    "coverPath": "books/starter/en-a2-course-cover.svg",
    "source": "Word Hunter Originals"
  },
  {
    "id": "starter-en-b1-course",
    "title": "The Quiet Mile: A B1 Graded Reader",
    "author": "Word Hunter Originals",
    "lang": "en",
    "level": "B1",
    "blurb": "An original B1 graded reader for reading comprehension and contextual vocabulary only.",
    "localPath": "books/starter/en-b1-course.txt",
    "coverPath": "books/starter/en-b1-course-cover.svg",
    "source": "Word Hunter Originals"
  },
  {
    "id": "starter-en-b2-course",
    "title": "The Space Between Voices: A B2 Graded Reader",
    "author": "Word Hunter Originals",
    "lang": "en",
    "level": "B2",
    "blurb": "An original B2 graded reader for reading comprehension and contextual vocabulary only.",
    "localPath": "books/starter/en-b2-course.txt",
    "coverPath": "books/starter/en-b2-course-cover.svg",
    "source": "Word Hunter Originals"
  },
  {
    "id": "starter-de-a1-course",
    "title": "Deutsch im Alltag: Gemeinsam ankommen A1",
    "author": "Word Hunter Originals",
    "lang": "de",
    "level": "A1",
    "blurb": "An original A1 graded reader for reading comprehension and contextual vocabulary only.",
    "localPath": "books/starter/de-a1-course.txt",
    "coverPath": "books/starter/de-a1-course-cover.svg",
    "source": "Word Hunter Originals"
  },
  {
    "id": "starter-de-a2-course",
    "title": "Zwischen Alltag und Aufbruch: Deutsch A2",
    "author": "Word Hunter Originals",
    "lang": "de",
    "level": "A2",
    "blurb": "An original A2 graded reader for reading comprehension and contextual vocabulary only.",
    "localPath": "books/starter/de-a2-course.txt",
    "coverPath": "books/starter/de-a2-course-cover.svg",
    "source": "Word Hunter Originals"
  },
  {
    "id": "starter-de-b1-course",
    "title": "Neue Wege, klare Worte: Deutsch B1",
    "author": "Word Hunter Originals",
    "lang": "de",
    "level": "B1",
    "blurb": "An original B1 graded reader for reading comprehension and contextual vocabulary only.",
    "localPath": "books/starter/de-b1-course.txt",
    "coverPath": "books/starter/de-b1-course-cover.svg",
    "source": "Word Hunter Originals"
  },
  {
    "id": "starter-de-b2-course",
    "title": "Perspektiven im Gespräch: Deutsch B2",
    "author": "Word Hunter Originals",
    "lang": "de",
    "level": "B2",
    "blurb": "An original B2 graded reader for reading comprehension and contextual vocabulary only.",
    "localPath": "books/starter/de-b2-course.txt",
    "coverPath": "books/starter/de-b2-course-cover.svg",
    "source": "Word Hunter Originals"
  },
  {
    "id": "starter-es-a1-course",
    "title": "Lectura graduada A1: Las ventanas de Puerto de Alba",
    "author": "Word Hunter Originals",
    "lang": "es",
    "level": "A1",
    "blurb": "An original A1 graded reader for reading comprehension and contextual vocabulary only.",
    "localPath": "books/starter/es-a1-course.txt",
    "coverPath": "books/starter/es-a1-course-cover.svg",
    "source": "Word Hunter Originals"
  },
  {
    "id": "starter-es-a2-course",
    "title": "Lectura graduada A2: Cartas desde el andén",
    "author": "Word Hunter Originals",
    "lang": "es",
    "level": "A2",
    "blurb": "An original A2 graded reader for reading comprehension and contextual vocabulary only.",
    "localPath": "books/starter/es-a2-course.txt",
    "coverPath": "books/starter/es-a2-course-cover.svg",
    "source": "Word Hunter Originals"
  },
  {
    "id": "starter-es-b1-course",
    "title": "Lectura graduada B1: Las voces que trae el río",
    "author": "Word Hunter Originals",
    "lang": "es",
    "level": "B1",
    "blurb": "An original B1 graded reader for reading comprehension and contextual vocabulary only.",
    "localPath": "books/starter/es-b1-course.txt",
    "coverPath": "books/starter/es-b1-course-cover.svg",
    "source": "Word Hunter Originals"
  },
  {
    "id": "starter-es-b2-course",
    "title": "Lectura graduada B2: La hora de todas las ventanas",
    "author": "Word Hunter Originals",
    "lang": "es",
    "level": "B2",
    "blurb": "An original B2 graded reader for reading comprehension and contextual vocabulary only.",
    "localPath": "books/starter/es-b2-course.txt",
    "coverPath": "books/starter/es-b2-course-cover.svg",
    "source": "Word Hunter Originals"
  },
  {
    "id": "starter-fr-a1-course",
    "title": "Les Jours de la Traverse",
    "author": "Word Hunter Originals",
    "lang": "fr",
    "level": "A1",
    "blurb": "An original A1 graded reader for reading comprehension and contextual vocabulary only.",
    "localPath": "books/starter/fr-a1-course.txt",
    "coverPath": "books/starter/fr-a1-course-cover.svg",
    "source": "Word Hunter Originals"
  },
  {
    "id": "starter-fr-a2-course",
    "title": "Les Voix de l’Hirondelle",
    "author": "Word Hunter Originals",
    "lang": "fr",
    "level": "A2",
    "blurb": "An original A2 graded reader for reading comprehension and contextual vocabulary only.",
    "localPath": "books/starter/fr-a2-course.txt",
    "coverPath": "books/starter/fr-a2-course-cover.svg",
    "source": "Word Hunter Originals"
  },
  {
    "id": "starter-fr-b1-course",
    "title": "Deux villes, une Traverse",
    "author": "Word Hunter Originals",
    "lang": "fr",
    "level": "B1",
    "blurb": "An original B1 graded reader for reading comprehension and contextual vocabulary only.",
    "localPath": "books/starter/fr-b1-course.txt",
    "coverPath": "books/starter/fr-b1-course-cover.svg",
    "source": "Word Hunter Originals"
  },
  {
    "id": "starter-fr-b2-course",
    "title": "La Maison des passages",
    "author": "Word Hunter Originals",
    "lang": "fr",
    "level": "B2",
    "blurb": "An original B2 graded reader for reading comprehension and contextual vocabulary only.",
    "localPath": "books/starter/fr-b2-course.txt",
    "coverPath": "books/starter/fr-b2-course-cover.svg",
    "source": "Word Hunter Originals"
  },
  {
    "id": "starter-it-a1-course",
    "title": "UNA MAPPA PER RESTARE",
    "author": "Word Hunter Originals",
    "lang": "it",
    "level": "A1",
    "blurb": "An original A1 graded reader for reading comprehension and contextual vocabulary only.",
    "localPath": "books/starter/it-a1-course.txt",
    "coverPath": "books/starter/it-a1-course-cover.svg",
    "source": "Word Hunter Originals"
  },
  {
    "id": "starter-it-a2-course",
    "title": "LE FINESTRE ACCESE",
    "author": "Word Hunter Originals",
    "lang": "it",
    "level": "A2",
    "blurb": "An original A2 graded reader for reading comprehension and contextual vocabulary only.",
    "localPath": "books/starter/it-a2-course.txt",
    "coverPath": "books/starter/it-a2-course-cover.svg",
    "source": "Word Hunter Originals"
  },
  {
    "id": "starter-it-b1-course",
    "title": "FUORI CAMPO",
    "author": "Word Hunter Originals",
    "lang": "it",
    "level": "B1",
    "blurb": "An original B1 graded reader for reading comprehension and contextual vocabulary only.",
    "localPath": "books/starter/it-b1-course.txt",
    "coverPath": "books/starter/it-b1-course-cover.svg",
    "source": "Word Hunter Originals"
  },
  {
    "id": "starter-it-b2-course",
    "title": "LE CITTÀ POSSIBILI",
    "author": "Word Hunter Originals",
    "lang": "it",
    "level": "B2",
    "blurb": "An original B2 graded reader for reading comprehension and contextual vocabulary only.",
    "localPath": "books/starter/it-b2-course.txt",
    "coverPath": "books/starter/it-b2-course-cover.svg",
    "source": "Word Hunter Originals"
  },
  {
    "id": "starter-pl-a1-course",
    "title": "Polski na co dzień. Czytanka A1",
    "author": "Word Hunter Originals",
    "lang": "pl",
    "level": "A1",
    "blurb": "An original A1 graded reader for reading comprehension and contextual vocabulary only.",
    "localPath": "books/starter/pl-a1-course.txt",
    "coverPath": "books/starter/pl-a1-course-cover.svg",
    "source": "Word Hunter Originals"
  },
  {
    "id": "starter-pl-a2-course",
    "title": "Polski w działaniu. Czytanka A2",
    "author": "Word Hunter Originals",
    "lang": "pl",
    "level": "A2",
    "blurb": "An original A2 graded reader for reading comprehension and contextual vocabulary only.",
    "localPath": "books/starter/pl-a2-course.txt",
    "coverPath": "books/starter/pl-a2-course-cover.svg",
    "source": "Word Hunter Originals"
  },
  {
    "id": "starter-pl-b1-course",
    "title": "Polski samodzielnie. Czytanka B1",
    "author": "Word Hunter Originals",
    "lang": "pl",
    "level": "B1",
    "blurb": "An original B1 graded reader for reading comprehension and contextual vocabulary only.",
    "localPath": "books/starter/pl-b1-course.txt",
    "coverPath": "books/starter/pl-b1-course-cover.svg",
    "source": "Word Hunter Originals"
  },
  {
    "id": "starter-pl-b2-course",
    "title": "Polski precyzyjnie. Czytanka B2",
    "author": "Word Hunter Originals",
    "lang": "pl",
    "level": "B2",
    "blurb": "An original B2 graded reader for reading comprehension and contextual vocabulary only.",
    "localPath": "books/starter/pl-b2-course.txt",
    "coverPath": "books/starter/pl-b2-course-cover.svg",
    "source": "Word Hunter Originals"
  },
  {
    "id": "starter-uk-a1-course",
    "title": "Українська крок за кроком. Читанка A1",
    "author": "Word Hunter Originals",
    "lang": "uk",
    "level": "A1",
    "blurb": "An original A1 graded reader for reading comprehension and contextual vocabulary only.",
    "localPath": "books/starter/uk-a1-course.txt",
    "coverPath": "books/starter/uk-a1-course-cover.svg",
    "source": "Word Hunter Originals"
  },
  {
    "id": "starter-uk-a2-course",
    "title": "Українська в дії. Читанка A2",
    "author": "Word Hunter Originals",
    "lang": "uk",
    "level": "A2",
    "blurb": "An original A2 graded reader for reading comprehension and contextual vocabulary only.",
    "localPath": "books/starter/uk-a2-course.txt",
    "coverPath": "books/starter/uk-a2-course-cover.svg",
    "source": "Word Hunter Originals"
  },
  {
    "id": "starter-uk-b1-course",
    "title": "Самостійно українською. Читанка B1",
    "author": "Word Hunter Originals",
    "lang": "uk",
    "level": "B1",
    "blurb": "An original B1 graded reader for reading comprehension and contextual vocabulary only.",
    "localPath": "books/starter/uk-b1-course.txt",
    "coverPath": "books/starter/uk-b1-course-cover.svg",
    "source": "Word Hunter Originals"
  },
  {
    "id": "starter-uk-b2-course",
    "title": "Аргументовано українською. Читанка B2",
    "author": "Word Hunter Originals",
    "lang": "uk",
    "level": "B2",
    "blurb": "An original B2 graded reader for reading comprehension and contextual vocabulary only.",
    "localPath": "books/starter/uk-b2-course.txt",
    "coverPath": "books/starter/uk-b2-course-cover.svg",
    "source": "Word Hunter Originals"
  },
  {
    "id": "starter-ru-a1-course",
    "title": "Окна Старого Берега — Фонарь во дворе. Книга для чтения A1",
    "author": "Word Hunter Originals",
    "lang": "ru",
    "level": "A1",
    "blurb": "An original A1 graded reader for reading comprehension and contextual vocabulary only.",
    "localPath": "books/starter/ru-a1-course.txt",
    "coverPath": "books/starter/ru-a1-course-cover.svg",
    "source": "Word Hunter Originals"
  },
  {
    "id": "starter-ru-a2-course",
    "title": "Окна Старого Берега — Летний зал. Адаптированное чтение A2",
    "author": "Word Hunter Originals",
    "lang": "ru",
    "level": "A2",
    "blurb": "An original A2 graded reader for reading comprehension and contextual vocabulary only.",
    "localPath": "books/starter/ru-a2-course.txt",
    "coverPath": "books/starter/ru-a2-course-cover.svg",
    "source": "Word Hunter Originals"
  },
  {
    "id": "starter-ru-b1-course",
    "title": "Окна Старого Берега — Город помнит по-разному. Книга для чтения B1",
    "author": "Word Hunter Originals",
    "lang": "ru",
    "level": "B1",
    "blurb": "An original B1 graded reader for reading comprehension and contextual vocabulary only.",
    "localPath": "books/starter/ru-b1-course.txt",
    "coverPath": "books/starter/ru-b1-course-cover.svg",
    "source": "Word Hunter Originals"
  },
  {
    "id": "starter-ru-b2-course",
    "title": "Окна Старого Берега — Право на свет. Адаптированное чтение B2",
    "author": "Word Hunter Originals",
    "lang": "ru",
    "level": "B2",
    "blurb": "An original B2 graded reader for reading comprehension and contextual vocabulary only.",
    "localPath": "books/starter/ru-b2-course.txt",
    "coverPath": "books/starter/ru-b2-course-cover.svg",
    "source": "Word Hunter Originals"
  },
  {
    "id": "starter-ja-a1-course",
    "title": "月舟文庫の春　日本語レベル別読み物 A1",
    "author": "Word Hunter Originals",
    "lang": "ja",
    "level": "A1",
    "blurb": "An original A1 graded reader for reading comprehension and contextual vocabulary only.",
    "localPath": "books/starter/ja-a1-course.txt",
    "coverPath": "books/starter/ja-a1-course-cover.svg",
    "source": "Word Hunter Originals"
  },
  {
    "id": "starter-ja-a2-course",
    "title": "月舟文庫と川風の地図　日本語レベル別読み物 A2",
    "author": "Word Hunter Originals",
    "lang": "ja",
    "level": "A2",
    "blurb": "An original A2 graded reader for reading comprehension and contextual vocabulary only.",
    "localPath": "books/starter/ja-a2-course.txt",
    "coverPath": "books/starter/ja-a2-course-cover.svg",
    "source": "Word Hunter Originals"
  },
  {
    "id": "starter-ja-b1-course",
    "title": "月舟文庫、町を歩く　日本語レベル別読み物 B1",
    "author": "Word Hunter Originals",
    "lang": "ja",
    "level": "B1",
    "blurb": "An original B1 graded reader for reading comprehension and contextual vocabulary only.",
    "localPath": "books/starter/ja-b1-course.txt",
    "coverPath": "books/starter/ja-b1-course-cover.svg",
    "source": "Word Hunter Originals"
  },
  {
    "id": "starter-ja-b2-course",
    "title": "月舟文庫の向こう岸　日本語レベル別読み物 B2",
    "author": "Word Hunter Originals",
    "lang": "ja",
    "level": "B2",
    "blurb": "An original B2 graded reader for reading comprehension and contextual vocabulary only.",
    "localPath": "books/starter/ja-b2-course.txt",
    "coverPath": "books/starter/ja-b2-course-cover.svg",
    "source": "Word Hunter Originals"
  },
  {
    "id": "starter-zh-a1-course",
    "title": "汉语A1分级读物：桂花巷的新钥匙",
    "author": "Word Hunter Originals",
    "lang": "zh",
    "level": "A1",
    "blurb": "An original A1 graded reader for reading comprehension and contextual vocabulary only.",
    "localPath": "books/starter/zh-a1-course.txt",
    "coverPath": "books/starter/zh-a1-course-cover.svg",
    "source": "Word Hunter Originals"
  },
  {
    "id": "starter-zh-a2-course",
    "title": "汉语A2分级读物：照片里的桂花巷",
    "author": "Word Hunter Originals",
    "lang": "zh",
    "level": "A2",
    "blurb": "An original A2 graded reader for reading comprehension and contextual vocabulary only.",
    "localPath": "books/starter/zh-a2-course.txt",
    "coverPath": "books/starter/zh-a2-course-cover.svg",
    "source": "Word Hunter Originals"
  },
  {
    "id": "starter-zh-b1-course",
    "title": "汉语B1分级读物：沿河六公里",
    "author": "Word Hunter Originals",
    "lang": "zh",
    "level": "B1",
    "blurb": "An original B1 graded reader for reading comprehension and contextual vocabulary only.",
    "localPath": "books/starter/zh-b1-course.txt",
    "coverPath": "books/starter/zh-b1-course-cover.svg",
    "source": "Word Hunter Originals"
  },
  {
    "id": "starter-zh-b2-course",
    "title": "汉语B2分级读物：厂门打开以前",
    "author": "Word Hunter Originals",
    "lang": "zh",
    "level": "B2",
    "blurb": "An original B2 graded reader for reading comprehension and contextual vocabulary only.",
    "localPath": "books/starter/zh-b2-course.txt",
    "coverPath": "books/starter/zh-b2-course-cover.svg",
    "source": "Word Hunter Originals"
  },
  {
    "id": "starter-la-a1-course",
    "title": "ARCA CUM DELPHINO",
    "author": "Word Hunter Originals",
    "lang": "la",
    "level": "A1",
    "blurb": "An original Latin graded reader for reading comprehension and contextual vocabulary only, with CEFR-inspired A1 reading difficulty.",
    "localPath": "books/starter/la-a1-course.txt",
    "coverPath": "books/starter/la-a1-course-cover.svg",
    "source": "Word Hunter Originals"
  },
  {
    "id": "starter-la-a2-course",
    "title": "VIA INTER DUOS PORTUS",
    "author": "Word Hunter Originals",
    "lang": "la",
    "level": "A2",
    "blurb": "An original Latin graded reader for reading comprehension and contextual vocabulary only, with CEFR-inspired A2 reading difficulty.",
    "localPath": "books/starter/la-a2-course.txt",
    "coverPath": "books/starter/la-a2-course-cover.svg",
    "source": "Word Hunter Originals"
  },
  {
    "id": "starter-la-b1-course",
    "title": "MEMORIA CANALIS",
    "author": "Word Hunter Originals",
    "lang": "la",
    "level": "B1",
    "blurb": "An original Latin graded reader for reading comprehension and contextual vocabulary only, with CEFR-inspired B1 reading difficulty.",
    "localPath": "books/starter/la-b1-course.txt",
    "coverPath": "books/starter/la-b1-course-cover.svg",
    "source": "Word Hunter Originals"
  },
  {
    "id": "starter-la-b2-course",
    "title": "LIMUS SUB AQUA",
    "author": "Word Hunter Originals",
    "lang": "la",
    "level": "B2",
    "blurb": "An original Latin graded reader for reading comprehension and contextual vocabulary only, with CEFR-inspired B2 reading difficulty.",
    "localPath": "books/starter/la-b2-course.txt",
    "coverPath": "books/starter/la-b2-course-cover.svg",
    "source": "Word Hunter Originals"
  },
  {
    "id": "starter-grc-a1-course",
    "title": "Ἀνάγνωσμα A1: Ὁ λύχνος τοῦ Κεραμεικοῦ",
    "author": "Word Hunter Originals",
    "lang": "grc",
    "level": "A1",
    "blurb": "An original Ancient Greek graded reader for reading comprehension and contextual vocabulary only, with CEFR-inspired A1 reading difficulty.",
    "localPath": "books/starter/grc-a1-course.txt",
    "coverPath": "books/starter/grc-a1-course-cover.svg",
    "source": "Word Hunter Originals"
  },
  {
    "id": "starter-grc-a2-course",
    "title": "Ἀνάγνωσμα A2: Ἡ σφραγὶς ἐν τῇ Ἱερᾷ Ὁδῷ",
    "author": "Word Hunter Originals",
    "lang": "grc",
    "level": "A2",
    "blurb": "An original Ancient Greek graded reader for reading comprehension and contextual vocabulary only, with CEFR-inspired A2 reading difficulty.",
    "localPath": "books/starter/grc-a2-course.txt",
    "coverPath": "books/starter/grc-a2-course-cover.svg",
    "source": "Word Hunter Originals"
  },
  {
    "id": "starter-grc-b1-course",
    "title": "Ἀνάγνωσμα B1: Τὰ γράμματα μετὰ τὴν θύελλαν",
    "author": "Word Hunter Originals",
    "lang": "grc",
    "level": "B1",
    "blurb": "An original Ancient Greek graded reader for reading comprehension and contextual vocabulary only, with CEFR-inspired B1 reading difficulty.",
    "localPath": "books/starter/grc-b1-course.txt",
    "coverPath": "books/starter/grc-b1-course-cover.svg",
    "source": "Word Hunter Originals"
  },
  {
    "id": "starter-grc-b2-course",
    "title": "Ἀνάγνωσμα B2: Ὁ λίθος καὶ ἡ θάλαττα",
    "author": "Word Hunter Originals",
    "lang": "grc",
    "level": "B2",
    "blurb": "An original Ancient Greek graded reader for reading comprehension and contextual vocabulary only, with CEFR-inspired B2 reading difficulty.",
    "localPath": "books/starter/grc-b2-course.txt",
    "coverPath": "books/starter/grc-b2-course-cover.svg",
    "source": "Word Hunter Originals"
  }
]
